test/__init__.py
test/freecad/__init__.py
test/freecad/test_permissions.py
test/freecad/test_run_and_simulate.py
test/python/__init__.py
test/python/test_notebooks.py
freecad.exp_optics_workbench-0.1.1.dist-info/METADATA
freecad.exp_optics_workbench-0.1.1.dist-info/WHEEL
freecad.exp_optics_workbench-0.1.1.dist-info/top_level.txt
freecad.exp_optics_workbench-0.1.1.dist-info/RECORD
