Metadata-Version: 2.1
Name: freecad.exp_optics_workbench
Version: 0.1.1
Summary: Physically accurate forward ray tracing for optics simulation and optimization with FreeCAD workbench frontend
Home-page: https://github.com/zaphB/optics_design_workbench
Author: Philipp Bredol
Author-email: philipp.bredol@rwth-aachen.de
Requires-Dist: numpy
Requires-Dist: scipy
Requires-Dist: matplotlib
Requires-Dist: atomicwrites
